pandoc_cover.py
pandoc_cover-0.2.1.dist-info/LICENSE
pandoc_cover-0.2.1.dist-info/METADATA
pandoc_cover-0.2.1.dist-info/WHEEL
pandoc_cover-0.2.1.dist-info/entry_points.txt
pandoc_cover-0.2.1.dist-info/top_level.txt
pandoc_cover-0.2.1.dist-info/RECORD
