Metadata-Version: 2.1
Name: pandoc-cover
Version: 0.2.1
Summary: Add a PDF cover to a document using an SVG template and the pandoc metadata 
Author-email: Damien Clochard <damien.clochard@dalibo.com>
Project-URL: Homepage, https://github.com/daamien/pandoc-cover
Project-URL: Bug Tracker, https://github.com/daamien/pandoc-cover/issues
Classifier: Programming Language :: Python :: 3
Classifier: License :: OSI Approved :: MIT License
Classifier: Operating System :: OS Independent
Requires-Python: >=3.7
License-File: LICENSE
Requires-Dist: panflute
Requires-Dist: jinja2
